transcribe_with_whisper/__init__.py
transcribe_with_whisper/html_to_docx.py
transcribe_with_whisper/main.py
transcribe_with_whisper/mercuryscribe.py
transcribe_with_whisper/server_app.py
transcribe_with_whisper-0.8.3.dist-info/METADATA
transcribe_with_whisper-0.8.3.dist-info/WHEEL
transcribe_with_whisper-0.8.3.dist-info/top_level.txt
transcribe_with_whisper-0.8.3.dist-info/RECORD
