Metadata-Version: 2.4
Name: transcribe-with-whisper
Version: 0.8.3
Summary: Add your description here
Home-page: https://github.com/literatecomputing/transcribe-with-whisper
Author: Jay Pfaffman
Requires-Python: >=3.8
Requires-Dist: asteroid-filterbanks>=0.4.0
Requires-Dist: fastapi==0.118.0
Requires-Dist: faster-whisper==1.2.0
Requires-Dist: htmldocx>=0.0.6
Requires-Dist: huggingface-hub==0.35.3
Requires-Dist: pyannote-audio==4.0.0
Requires-Dist: pydub==0.25.1
Requires-Dist: python-docx>=0.8.12
Requires-Dist: python-multipart==0.0.20
Requires-Dist: torch==2.8.0
Requires-Dist: uvicorn[standard]==0.37.0
Requires-Dist: webvtt-py==0.5.1
Dynamic: author
Dynamic: home-page
Dynamic: requires-python
